xlwombat/__init__.py
xlwombat/worksheet.py
xlwombat-0.1.0.dist-info/WHEEL
xlwombat-0.1.0.dist-info/METADATA
xlwombat-0.1.0.dist-info/RECORD
